{
  "id": "MAP_ROUGH_CAVE_B2",
  "name": "RoughCaveB2",
  "layout": "LAYOUT_ROUGH_CAVE_B2",
  "music": "MUS_PETALBURG_WOODS",
  "region_map_section": "MAPSEC_ROUGH_CAVE",
  "requires_flash": false,
  "weather": "WEATHER_NONE",
  "map_type": "MAP_TYPE_UNDERGROUND",
  "allow_cycling": true,
  "allow_escaping": true,
  "allow_running": true,
  "show_map_name": true,
  "battle_scene": "MAP_BATTLE_SCENE_NORMAL",
  "connections": 0,
  "object_events": [
    {
      "graphics_id": "OBJ_EVENT_GFX_ITEM_BALL",
      "x": 12,
      "y": 16,
      "elevation": 0,
      "movement_type": "MOVEMENT_TYPE_NONE",
      "movement_range_x": 0,
      "movement_range_y": 0,
      "trainer_type": "TRAINER_TYPE_SEE_ALL_DIRECTIONS",
      "trainer_sight_or_berry_tree_id": "ITEM_TM57",
      "script": "Common_EventScript_FindItem",
      "flag": "FLAG_ITEM_ROUGH_CAVE_TM57"
    },
    {
      "graphics_id": "OBJ_EVENT_GFX_ITEM_BALL",
      "x": 32,
      "y": 27,
      "elevation": 0,
      "movement_type": "MOVEMENT_TYPE_NONE",
      "movement_range_x": 0,
      "movement_range_y": 0,
      "trainer_type": "TRAINER_TYPE_SEE_ALL_DIRECTIONS",
      "trainer_sight_or_berry_tree_id": "ITEM_NEVER_MELT_ICE",
      "script": "Common_EventScript_FindItem",
      "flag": "FLAG_ITEM_ROUGH_CAVE_NEVER_MELT_ICE"
    },
    {
      "graphics_id": "OBJ_EVENT_GFX_ITEM_BALL",
      "x": 3,
      "y": 18,
      "elevation": 0,
      "movement_type": "MOVEMENT_TYPE_NONE",
      "movement_range_x": 0,
      "movement_range_y": 0,
      "trainer_type": "TRAINER_TYPE_SEE_ALL_DIRECTIONS",
      "trainer_sight_or_berry_tree_id": "ITEM_ICE_STONE",
      "script": "Common_EventScript_FindItem",
      "flag": "FLAG_ITEM_ROUGH_CAVE_ICE_STONE"
    },
    {
      "graphics_id": "OBJ_EVENT_GFX_WOMAN_5",
      "x": 12,
      "y": 19,
      "elevation": 0,
      "movement_type": "MOVEMENT_TYPE_FACE_RIGHT",
      "movement_range_x": 0,
      "movement_range_y": 0,
      "trainer_type": "TRAINER_TYPE_NORMAL",
      "trainer_sight_or_berry_tree_id": "4",
      "script": "RoughCaveB2_EventScript_AnelaceBattle",
      "flag": "0"
    }
  ],
  "warp_events": [
    {
      "x": 2,
      "y": 25,
      "elevation": 0,
      "dest_map": "MAP_ROUGH_CAVE_B1",
      "dest_warp_id": "1"
    }
  ],
  "coord_events": [

  ],
  "bg_events": [

  ]
}
